DSViz/ArrayListV.py
DSViz/BinaryTreeV.py
DSViz/GraphV.py
DSViz/LinkedListV.py
DSViz/NoneError.py
DSViz/__init__.py
DSViz/arrow.png
DSViz/doubleArrow.png
DataStructureVisualiser-1.0.3.dist-info/LICENSE
DataStructureVisualiser-1.0.3.dist-info/METADATA
DataStructureVisualiser-1.0.3.dist-info/WHEEL
DataStructureVisualiser-1.0.3.dist-info/top_level.txt
DataStructureVisualiser-1.0.3.dist-info/RECORD
