Metadata-Version: 2.1
Name: DataStructureVisualiser
Version: 1.0.3
Summary: DSViz is a simple and intuitive Python interface to multiple packages in order to help visualise different data structres while coding them. This package is developed mainly for students or developers who are in the process of learning data structures.
Home-page: https://github.com/IshMehta/DSViz
Author: Ish Mehta
Author-email: imehta34@gatech.edu
License: MIT
Project-URL: GitHub, https://github.com/IshMehta/DSViz
Project-URL: Documentation, https://ishmehta.github.io/DSViz/
Keywords: data structure,graph,list,array,tree,BST,AVL,binary,draw,visualise
Platform: UNKNOWN
Classifier: Development Status :: 3 - Alpha
Classifier: Intended Audience :: Education
Classifier: Topic :: Education
Classifier: License :: OSI Approved :: MIT License
Classifier: Operating System :: OS Independent
Classifier: Programming Language :: Python :: 3
Requires-Dist: tk
Requires-Dist: graphviz
Requires-Dist: pillow
